{"cameraMode":{"drawMode":0,"name":"Shaded","section":"Shading Mode"},"sceneLighting":false,"audioPlay":false,"sceneViewState":{"m_AlwaysRefresh":false,"showFog":true,"showSkybox":false,"showFlares":true,"showImageEffects":true,"showParticleSystems":true,"showVisualEffectGraphs":true,"m_FxEnabled":true},"in2DMode":false,"pivot":{"x":2.002533197402954,"y":-2.978069543838501,"z":-0.31527382135391238},"rotation":{"x":-0.10157591104507446,"y":-0.23467674851417542,"z":0.024646462872624399,"w":-0.9664857387542725},"size":0.566658616065979,"orthographic":false}